page_explorer/__init__.py
page_explorer/__main__.py
page_explorer/args.py
page_explorer/main.py
page_explorer/page_explorer.py
page_explorer/py.typed
page_explorer/test_main.py
page_explorer/test_page_explorer.py
page_explorer-0.8.1.dist-info/licenses/LICENSE.md
page_explorer-0.8.1.dist-info/METADATA
page_explorer-0.8.1.dist-info/WHEEL
page_explorer-0.8.1.dist-info/entry_points.txt
page_explorer-0.8.1.dist-info/top_level.txt
page_explorer-0.8.1.dist-info/RECORD
